crijndael.cpython-311-i386-linux-musl.so
crijndael-1.0.2.dist-info/METADATA
crijndael-1.0.2.dist-info/WHEEL
crijndael-1.0.2.dist-info/LICENSE
crijndael-1.0.2.dist-info/top_level.txt
crijndael-1.0.2.dist-info/RECORD
